ezybaas
fdvdfv
