Metadata-Version: 2.1
Name: django-ezybaas
Version: 0.1.4
Summary: Easiest BaaS. Idea to APIs instantly on SQL DBs!
Home-page: https://www.ezybaas.com/
Author: Bhavik Shah
Author-email: bhavik@susthitsoft.com
License: Apache License
Keywords: django,rest,database,api,baas,backed
Platform: any
Classifier: Environment :: Web Environment
Classifier: Framework :: Django
Classifier: Intended Audience :: Developers
Classifier: License :: OSI Approved :: Apache Software License
Classifier: Operating System :: OS Independent
Classifier: Programming Language :: Python
Classifier: Programming Language :: Python :: 3.5
Classifier: Programming Language :: Python :: 3.6
Classifier: Programming Language :: Python :: 3.7
Classifier: Programming Language :: Python :: 3.8
Classifier: Topic :: Internet :: WWW/HTTP
Classifier: Topic :: Internet :: WWW/HTTP :: WSGI :: Application
Classifier: Topic :: Software Development
Classifier: Topic :: Database :: Front-Ends
Classifier: Topic :: Internet :: WWW/HTTP :: Dynamic Content
